aceiot_models/__init__.py
aceiot_models/bacnet.py
aceiot_models/cache.py
aceiot_models/clients.py
aceiot_models/common.py
aceiot_models/config.py
aceiot_models/der_events.py
aceiot_models/events.py
aceiot_models/exceptions.py
aceiot_models/gateways.py
aceiot_models/hawke.py
aceiot_models/model_factory.py
aceiot_models/points.py
aceiot_models/sample.py
aceiot_models/serializers.py
aceiot_models/sites.py
aceiot_models/timeseries.py
aceiot_models/typing_protocols.py
aceiot_models/users.py
aceiot_models/validators.py
aceiot_models/volttron.py
aceiot_models/api/__init__.py
aceiot_models/api/client.py
aceiot_models/api/pagination.py
aceiot_models/api/utils.py
aceiot_models-0.3.4.dist-info/METADATA
aceiot_models-0.3.4.dist-info/WHEEL
aceiot_models-0.3.4.dist-info/licenses/LICENSE
aceiot_models-0.3.4.dist-info/RECORD
