Metadata-Version: 2.4
Name: aceiot-models
Version: 0.3.4
Summary: Pydantic models and API client for ACE IoT Aerodrome platform
Project-URL: Homepage, https://github.com/ACE-IoT-Solutions/aceiot-models
Project-URL: Repository, https://github.com/ACE-IoT-Solutions/aceiot-models.git
Project-URL: Issues, https://github.com/ACE-IoT-Solutions/aceiot-models/issues
Author-email: Andrew Rodgers <andrew@aceiotsolutions.com>
Maintainer-email: Andrew Rodgers <andrew@aceiotsolutions.com>
License: MIT
License-File: LICENSE
Keywords: aceiot,api,client,iot,pydantic,sdk
Classifier: Development Status :: 4 - Beta
Classifier: Intended Audience :: Developers
Classifier: License :: OSI Approved :: MIT License
Classifier: Programming Language :: Python :: 3
Classifier: Programming Language :: Python :: 3.10
Classifier: Programming Language :: Python :: 3.11
Classifier: Programming Language :: Python :: 3.12
Classifier: Programming Language :: Python :: 3.13
Classifier: Topic :: Software Development :: Libraries :: Python Modules
Requires-Python: >=3.10
Requires-Dist: email-validator>=2.1.0
Requires-Dist: pydantic>=2.11.7
Requires-Dist: python-dateutil>=2.8.0
Requires-Dist: pytz>=2025.2
Requires-Dist: pyyaml>=6.0.2
Requires-Dist: requests>=2.31.0
Requires-Dist: toml>=0.10.2
Requires-Dist: urllib3>=2.0.0
Provides-Extra: upload-progress
Requires-Dist: requests-toolbelt>=1.0.0; extra == 'upload-progress'
